# 字节码

## 这个问题为什么存在？

> 从「没有这个东西会怎样」出发，解释问题的根源。

在没有字节码的时代，程序直接编译为**本地机器码**：

```
C语言程序 → 编译为x86机器码 → 只能在x86 CPU上运行
```

**痛点**：
1. **平台绑定**：同一份代码需要为Windows、Linux、Mac分别编译
2. **硬件绑定**：x86的程序不能在ARM上运行
3. **难以跨语言**：不同语言编译的二进制不兼容

**核心问题**：如何让同一份代码，在任何支持Java的平台上都能正确执行？

字节码（Bytecode）的本质是**虚拟机器指令集**：它是Java编译器输出的**中间代码**，由JVM解释或编译执行。

**为什么需要字节码？**
- **跨平台**：同一份字节码，在任何有JVM的平台上都能运行
- **安全性**：JVM在加载字节码时会进行**字节码校验**，防止恶意代码
- **优化空间**：JIT编译器可以在运行时对字节码进行深度优化

## 它是怎么解决问题的？

> 不止讲「是什么」，要讲清楚「为什么这样设计能解决问题」。

### 核心机制

#### 1. 字节码文件结构（.class文件）

```
┌─────────────────────────────────────────────────────────────┐
│                  .class 文件结构                             │
│                                                             │
│  ┌─────────────────────────────────────────────────────┐    │
│  │  魔数（Magic Number）                              │    │
│  │  0xCAFEBABE（咖啡宝贝）                          │    │
│  └─────────────────────────────────────────────────────┘    │
│                     │                                      │
│                     ▼                                      │
│  ┌─────────────────────────────────────────────────────┐    │
│  │  版本号（Minor Version + Major Version）            │    │
│  │  JDK 8 = 0x0034 (52)                           │    │
│  └─────────────────────────────────────────────────────┘    │
│                     │                                      │
│                     ▼                                      │
│  ┌─────────────────────────────────────────────────────┐    │
│  │  常量池（Constant Pool）                          │    │
│  │  存放字面量、符号引用、类和接口的全限定名        │    │
│  └─────────────────────────────────────────────────────┘    │
│                     │                                      │
│                     ▼                                      │
│  ┌─────────────────────────────────────────────────────┐    │
│  │  访问标志（Access Flags）                        │    │
│  │  public、final、abstract、interface等              │    │
│  └─────────────────────────────────────────────────────┘    │
│                     │                                      │
│                     ▼                                      │
│  ┌─────────────────────────────────────────────────────┐    │
│  │  类索引、父类索引、接口索引集合                  │    │
│  └─────────────────────────────────────────────────────┘    │
│                     │                                      │
│                     ▼                                      │
│  ┌─────────────────────────────────────────────────────┐    │
│  │  字段表集合（Fields）                           │    │
│  └─────────────────────────────────────────────────────┘    │
│                     │                                      │
│                     ▼                                      │
│  ┌─────────────────────────────────────────────────────┐    │
│  │  方法表集合（Methods）                          │    │
│  │  包含字节码指令                               │    │
│  └─────────────────────────────────────────────────────┘    │
│                     │                                      │
│                     ▼                                      │
│  ┌─────────────────────────────────────────────────────┐    │
│  │  属性表集合（Attributes）                        │    │
│  │  Code、LineNumberTable、LocalVariableTable等    │    │
│  └─────────────────────────────────────────────────────┘    │
└─────────────────────────────────────────────────────────────┘
```

**为什么需要魔数？**
- 快速判断文件是否为合法的.class文件
- 避免读取非class文件导致解析错误

**为什么需要常量池？**
- 字节码指令无法直接引用其他类、方法、字段
- 通过常量池中的**符号引用**，在运行时再解析为**直接引用**

#### 2. 字节码指令集（Bytecode Instruction Set）

Java字节码有约200个指令，分为以下几类：

```java
// 示例：int c = a + b 的字节码
public void test() {
    int a = 1;
    int b = 2;
    int c = a + b;
}
```

对应的字节码（使用`javap -c`查看）：
```
public void test();
    Code:
       0: iconst_1      // 将int类型常量1压入操作数栈
       1: istore_1    // 将操作数栈顶元素（1）存入局部变量表1（a）
       2: iconst_2      // 将int类型常量2压入操作数栈
       3: istore_2    // 将操作数栈顶元素（2）存入局部变量表2（b）
       4: iload_1      // 从局部变量表1（a）加载到操作数栈
       5: iload_2      // 从局部变量表2（b）加载到操作数栈
       6: iadd          // 弹出栈顶两个元素，相加，结果压入栈
       7: istore_3    // 将栈顶元素存入局部变量表3（c）
       8: return        // 方法返回
```

**字节码指令的设计思想**：
- **栈架构**：所有计算都在操作数栈上进行，指令短小（多为1字节）
- **类型区分**：`iadd`（int加法）、`ladd`（long加法）、`fadd`（float加法）— 针对不同类型有不同的指令

#### 3. 字节码执行过程

```
┌─────────────────────────────────────────────────────────────┐
│                  字节码执行过程                             │
│                                                             │
│  字节码指令 → 解释器 → 执行引擎                            │
│       │                                        │
│       ▼                                        │
│  ┌─────────────────────────────────────────┐            │
│  │  程序计数器（PC）                          │            │
│  │  记录当前执行的字节码偏移量                    │            │
│  └─────────────────────────────────────────┘            │
│       │                                              │
│       ▼                                              │
│  ┌─────────────────────────────────────────┐            │
│  │  操作数栈（Operand Stack）                   │            │
│  │  字节码指令从这里弹出操作数，计算结果压入    │            │
│  └─────────────────────────────────────────┘            │
│       │                                              │
│       ▼                                              │
│  ┌─────────────────────────────────────────┐            │
│  │  局部变量表（Local Variables）                │            │
│  │  存放方法参数和局部变量                      │            │
│  └─────────────────────────────────────────┘            │
│       │                                              │
│       ▼                                              │
│  ┌─────────────────────────────────────────┐            │
│  │  如果频繁执行 → JIT编译器 → 本地机器码         │            │
│  └─────────────────────────────────────────┘            │
└─────────────────────────────────────────────────────────────┘
```

### 源码关键路径

#### javac编译过程

```java
// JDK源码：javac编译器的主要流程
public class JavaCompiler {
    public void compile(List<JavaFileObject> sourceFileObjects) {
        // 1. 词法分析（Lexical Analysis）
        Lexer lexer = new Lexer(source);
        Tokens tokens = lexer.scan();
        
        // 2. 语法分析（Syntax Analysis）
        Parser parser = new Parser(tokens);
        AST ast = parser.parse();
        
        // 3. 语义分析（Semantic Analysis）
        SemanticAnalyzer semantic = new SemanticAnalyzer(ast);
        semantic.analyze();
        
        // 4. 字节码生成（Code Generation）
        CodeGenerator gen = new CodeGenerator(ast);
        gen.generate(sourceFileObjects);
    }
}
```

**为什么需要这么多步骤？**
- **词法分析**：将源代码转换为Token流
- **语法分析**：将Token流转换为抽象语法树（AST）
- **语义分析**：检查类型、作用域等语义正确性
- **字节码生成**：将AST转换为字节码指令

## 它和相似方案的本质区别是什么？

> 对比不是列表，要解释「为什么选 A 不选 B」。

### 字节码 vs 本地机器码

| 维度 | 字节码（Bytecode） | 本地机器码（Native Code） |
|------|---------------------|--------------------------|
| **跨平台性** | 强（JVM执行） | 弱（需重新编译） |
| **执行速度** | 慢（需要JVM解释/JIT） | 快（直接执行） |
| **安全性** | 高（字节码校验） | 低（可以执行任意指令） |
| **文件大小** | 较大（指令多） | 较小（指令少） |

**为什么选字节码？**
- **跨平台性**：同一份字节码，到处运行
- **安全性**：JVM可以对字节码进行校验，防止恶意代码

**为什么选本地机器码？**
- **执行速度**：无JVM中间层，直接执行
- **适合系统级编程**：操作系统、驱动程序

### 字节码 vs 抽象语法树（AST）

| 维度 | 字节码 | AST |
|------|--------|-----|
| **作用** | 可执行（JVM执行） | 不可执行（仅表示代码结构） |
| **生成阶段** | 编译后期 | 编译中期 |
| **使用场景** | JVM执行、反编译 | 语法分析、代码生成 |

**为什么需要AST？**
- AST是**结构化**的代码表示，便于语义分析和代码生成
- 字节码是**线性**的指令序列，便于执行

## 正确使用方式

> 不是 API 手册，要解释「为什么这样用是对的」。

### 1. 使用javap反编译.class文件

```bash
# 1. 查看字节码指令
javap -c MyClass.class

# 2. 查看详细信息（常量池、局部变量表等）
javap -v MyClass.class

# 3. 只查看public方法
javap -public MyClass.class
```

**为什么需要反编译？**
- 线上问题排查：查看编译器生成的字节码，理解底层行为
- 性能优化：查看是否进行了编译优化

### 2. 使用ASM或ByteBuddy操作字节码

```java
// 使用ASM生成一个简单的类
public class ASMGenerator {
    public static void main(String[] args) throws Exception {
        ClassWriter cw = new ClassWriter(0);
        cw.visit(Opcodes.V1_8, Opcodes.ACC_PUBLIC + Opcodes.ACC_SUPER,
                "HelloWorld", null, "java/lang/Object", null);
        
        // 生成main方法
        MethodVisitor mv = cw.visitMethod(
            Opcodes.ACC_PUBLIC + Opcodes.ACC_STATIC,
            "main",
            "([Ljava/lang/String;)V",
            null, null);
        mv.visitCode();
        mv.visitFieldInsn(Opcodes.GETSTATIC,
                "java/lang/System", "out", "Ljava/io/PrintStream;");
        mv.visitLdcInsn("Hello, World!");
        mv.visitMethodInsn(Opcodes.INVOKEVIRTUAL,
                "java/io/PrintStream", "println",
                "(Ljava/lang/String;)V", false);
        mv.visitInsn(Opcodes.RETURN);
        mv.visitMaxs(2, 1);
        mv.visitEnd();
        
        // 输出.class文件
        byte[] code = cw.toByteArray();
        FileOutputStream fos = new FileOutputStream("HelloWorld.class");
        fos.write(code);
        fos.close();
    }
}
```

**为什么需要操作字节码？**
- **动态生成类**：如Spring的AOP、Hibernate的代理
- **性能监控**：在方法入口/出口插入监控代码

### 3. 理解常见的字节码指令

```java
// Java代码
public int add(int a, int b) {
    return a + b;
}
```

```
// 字节码
public int add(int, int);
    Code:
       0: iload_1    // 加载参数a
       1: iload_2    // 加载参数b
       2: iadd       // 相加
       3: ireturn     // 返回int
```

**为什么需要理解字节码？**
- **理解JVM行为**：如`String +=`操作会生成`StringBuilder`
- **性能优化**：避免生成不必要的字节码指令

## 边界情况和坑

> 不是列举，要解释「坑的成因」。

### 坑1：字节码校验失败

```java
// 修改后的字节码（不合法）
// 如果手动修改.class文件，可能导致校验失败
java.lang.VerifyError: Bad <init> method call from inside of a constructor
```

**成因**：JVM在加载字节码时会进行**字节码校验**，确保：
1. 操作数栈不会溢出
2. 指令操作数类型正确
3. 跳转指令不会跳转到方法外部

**解决方案**：不要手动修改.class文件，使用ASM等库来操作字节码。

### 坑2：常量池过大

```java
// 如果有太多字符串字面量，常量池会非常大
public class BigConstantPool {
    public static void main(String[] args) {
        // 假设有100000个不同的字符串字面量
        // 常量池会非常大，导致JVM加载类很慢
    }
}
```

**成因**：每个字符串字面量、每个类/方法/字段引用都会占用常量池空间。

**解决方案**：避免在代码中直接使用大量字符串字面量，改用配置文件。

### 坑3：方法字节码超过64KB

```java
// 方法的字节码不能超过64KB
public class BigMethod {
    // 如果方法太大（如自动生成的代码），javac会报错：
    // "code too large"
}
```

**成因**：字节码文件中，方法的Code属性中的code_length字段是u4类型（32位），但实际限制是65535字节。

**解决方案**：拆分大方法为多个小方法。

## 我的理解（可选）

> 用自己的话重新表述一遍，检验是否真正理解。

字节码是Java实现**跨平台**的关键：它将Java源代码编译为一种**虚拟机器指令集**，由JVM解释或编译执行。

**核心思想**：
- **栈架构**：所有计算都在操作数栈上进行
- **类型区分**：不同数据类型有不同的指令（iadd、ladd等）
- **符号引用**：常量池中存放符号引用，运行时再解析为直接引用

**为什么需要字节码？**
- **跨平台**：同一份字节码，到处运行
- **安全性**：JVM可以对字节码进行校验
- **优化空间**：JIT编译器可以在运行时进行深度优化

**最容易被忽略的点**：
- 字节码校验可以捕获许多非法操作
- 常量池大小会影响JVM加载类的速度
- 方法的字节码不能超过64KB

## 面试话术总结

1. **字节码文件结构？**
   "字节码文件（.class）包含：魔数（0xCAFEBABE）、版本号、常量池、访问标志、类/父类/接口索引、字段表、方法表、属性表。其中常量池是核心，存放字面量和符号引用。"

2. **字节码指令有哪些类型？**
   "主要分为：1）加载和存储指令（iload、istore）；2）运算指令（iadd、isub）；3）类型转换指令（i2l、i2f）；4）对象创建和访问指令（new、getfield）；5）操作数栈管理指令（pop、dup）；6）控制转移指令（ifeq、goto）；7）方法调用和返回指令（invokevirtual、ireturn）。"

3. **为什么字节码是栈架构？**
   "栈架构指令短小（多为1字节），因为操作数隐含在操作数栈中，不需要显式指定操作数位置。而基于寄存器的架构（如Dalvik VM）需要指定寄存器编号，指令会更长。"

4. **如何查看字节码？**
   "使用javap命令：1）javap -c MyClass.class 查看字节码指令；2）javap -v MyClass.class 查看详细信息（常量池、局部变量表等）；3）javap -public MyClass.class 只查看public方法。"

5. **字节码操作有哪些应用？**
   "1）动态生成类（如Spring AOP、Hibernate代理）；2）性能监控（在方法入口/出口插入监控代码）；3）代码增强（如Lombok生成getter/setter）；4）反编译和逆向工程。"
